uvw/__init__.py
uvw/_version.py
uvw/data_array.py
uvw/parallel.py
uvw/unstructured.py
uvw/vtk_files.py
uvw/writer.py
uvw/dropin/__init__.py
uvw/dropin/hl.py
uvw-0.7.0.dist-info/LICENSE.md
uvw-0.7.0.dist-info/METADATA
uvw-0.7.0.dist-info/WHEEL
uvw-0.7.0.dist-info/top_level.txt
uvw-0.7.0.dist-info/RECORD
