Metadata-Version: 2.1
Name: uvw
Version: 0.7.0
Summary: Universal VTK Writer for Numpy Arrays
Home-page: https://github.com/prs513rosewood/uvw
Author: Lucas Frérot
Author-email: lucas.frerot@protonmail.com
Classifier: Programming Language :: Python :: 3
Classifier: License :: OSI Approved :: MIT License
Classifier: Operating System :: OS Independent
Classifier: Topic :: Scientific/Engineering :: Visualization
Classifier: Intended Audience :: Science/Research
License-File: LICENSE.md
Requires-Dist: numpy
Provides-Extra: mpi
Requires-Dist: mpi4py ; extra == 'mpi'
Provides-Extra: tests
Requires-Dist: pytest ; extra == 'tests'
Requires-Dist: pytest-mpi ; extra == 'tests'
Requires-Dist: pytest-cov ; extra == 'tests'
Requires-Dist: mpi4py ; extra == 'tests'
Requires-Dist: vtk ; extra == 'tests'
